common_hj3415/__init__.py
common_hj3415/domain/__init__.py
common_hj3415/domain/invirants.py
common_hj3415/domain/policies.py
common_hj3415/domain/types.py
common_hj3415/utils/__init__.py
common_hj3415/utils/numbers.py
common_hj3415/utils/strings.py
common_hj3415/utils/time.py
common_hj3415-0.2.0.dist-info/licenses/LICENSE
common_hj3415-0.2.0.dist-info/WHEEL
common_hj3415-0.2.0.dist-info/METADATA
common_hj3415-0.2.0.dist-info/RECORD
