Metadata-Version: 2.4
Name: common-hj3415
Version: 0.2.0
Summary: Shared tools for hj3415 projects
Keywords: example,demo
Author-email: Hyungjin Kim <hj3415@gmail.com>
Requires-Python: >=3.11
Classifier: Programming Language :: Python :: 3
Classifier: License :: OSI Approved :: MIT License
Classifier: Typing :: Typed
License-File: LICENSE
